README.md
setup.py
src/oidcendpoint/__init__.py
src/oidcendpoint/authn_event.py
src/oidcendpoint/client_authn.py
src/oidcendpoint/cookie.py
src/oidcendpoint/endpoint.py
src/oidcendpoint/endpoint_context.py
src/oidcendpoint/exception.py
src/oidcendpoint/grant.py
src/oidcendpoint/id_token.py
src/oidcendpoint/in_memory_db.py
src/oidcendpoint/jwt_token.py
src/oidcendpoint/list_db.py
src/oidcendpoint/login_hint.py
src/oidcendpoint/scopes.py
src/oidcendpoint/session.py
src/oidcendpoint/shelve_db.py
src/oidcendpoint/sso_db.py
src/oidcendpoint/template_handler.py
src/oidcendpoint/token_handler.py
src/oidcendpoint/userinfo.py
src/oidcendpoint/util.py
src/oidcendpoint.egg-info/PKG-INFO
src/oidcendpoint.egg-info/SOURCES.txt
src/oidcendpoint.egg-info/dependency_links.txt
src/oidcendpoint.egg-info/not-zip-safe
src/oidcendpoint.egg-info/requires.txt
src/oidcendpoint.egg-info/top_level.txt
src/oidcendpoint/authz/__init__.py
src/oidcendpoint/common/__init__.py
src/oidcendpoint/common/authorization.py
src/oidcendpoint/oauth2/__init__.py
src/oidcendpoint/oauth2/authorization.py
src/oidcendpoint/oauth2/device_authorization.py
src/oidcendpoint/oauth2/introspection.py
src/oidcendpoint/oauth2/pushed_authorization.py
src/oidcendpoint/oidc/__init__.py
src/oidcendpoint/oidc/authorization.py
src/oidcendpoint/oidc/discovery.py
src/oidcendpoint/oidc/provider_config.py
src/oidcendpoint/oidc/read_registration.py
src/oidcendpoint/oidc/refresh_token.py
src/oidcendpoint/oidc/registration.py
src/oidcendpoint/oidc/session.py
src/oidcendpoint/oidc/token.py
src/oidcendpoint/oidc/token_coop.py
src/oidcendpoint/oidc/userinfo.py
src/oidcendpoint/oidc/add_on/__init__.py
src/oidcendpoint/oidc/add_on/custom_scopes.py
src/oidcendpoint/oidc/add_on/pkce.py
src/oidcendpoint/user_authn/__init__.py
src/oidcendpoint/user_authn/authn_context.py
src/oidcendpoint/user_authn/user.py
src/oidcendpoint/user_info/__init__.py