Metadata-Version: 2.1
Name: oidcendpoint
Version: 1.0.1
Summary: Python implementation of OAuth2 AS and OpenID Connect OP
Home-page: https://github.com/IdentityPython/oicsrv
Author: Roland Hedberg
Author-email: roland@catalogix.se
License: Apache 2.0
Platform: UNKNOWN
Classifier: Development Status :: 4 - Beta
Classifier: License :: OSI Approved :: Apache Software License
Classifier: Programming Language :: Python :: 3.6
Classifier: Programming Language :: Python :: 3.7
Classifier: Programming Language :: Python :: 3.8
Classifier: Topic :: Software Development :: Libraries :: Python Modules
Provides-Extra: docs
Provides-Extra: quality
